{
  "generated_at": 1777713960395,
  "offers": [
    {
      "offer_id": "B09YCLG5PB__keepa_new_1",
      "asin": "B09YCLG5PB",
      "model": "4090",
      "title": "MSI GeForce RTX 4090 Gaming X Trio 24G Gaming Graphics Card - 24GB GDDR6X, 2595 MHz, PCI Express Gen 4, 384-bit, 3X DP v 1.4a, HDMI 2.1a (Supports 4K & 8K HDR)",
      "condition": "new",
      "condition_note": "lowest current new (Keepa)",
      "price_usd": 3740,
      "currency": "USD",
      "seller": null,
      "seller_id": null,
      "seller_rating": null,
      "seller_rating_count": null,
      "ships_from": null,
      "delivery_text": null,
      "first_seen": 1777713960395,
      "last_seen": 1777713960395,
      "is_buybox": true
    },
    {
      "offer_id": "B09YCLG5PB__keepa_used-good_2",
      "asin": "B09YCLG5PB",
      "model": "4090",
      "title": "MSI GeForce RTX 4090 Gaming X Trio 24G Gaming Graphics Card - 24GB GDDR6X, 2595 MHz, PCI Express Gen 4, 384-bit, 3X DP v 1.4a, HDMI 2.1a (Supports 4K & 8K HDR)",
      "condition": "used-good",
      "condition_note": "lowest current used (Keepa)",
      "price_usd": 3455.22,
      "currency": "USD",
      "seller": null,
      "seller_id": null,
      "seller_rating": null,
      "seller_rating_count": null,
      "ships_from": null,
      "delivery_text": null,
      "first_seen": 1777713960395,
      "last_seen": 1777713960395,
      "is_buybox": false
    },
    {
      "offer_id": "B0BJFRT43X__keepa_new_1",
      "asin": "B0BJFRT43X",
      "model": "4090",
      "title": "VIPERA NVIDIA GeForce RTX 4090 Founders Edition Graphic Card",
      "condition": "new",
      "condition_note": "lowest current new (Keepa)",
      "price_usd": 3840,
      "currency": "USD",
      "seller": null,
      "seller_id": null,
      "seller_rating": null,
      "seller_rating_count": null,
      "ships_from": null,
      "delivery_text": null,
      "first_seen": 1777713960395,
      "last_seen": 1777713960395,
      "is_buybox": true
    },
    {
      "offer_id": "B0BJFRT43X__keepa_used-good_2",
      "asin": "B0BJFRT43X",
      "model": "4090",
      "title": "VIPERA NVIDIA GeForce RTX 4090 Founders Edition Graphic Card",
      "condition": "used-good",
      "condition_note": "lowest current used (Keepa)",
      "price_usd": 2744,
      "currency": "USD",
      "seller": null,
      "seller_id": null,
      "seller_rating": null,
      "seller_rating_count": null,
      "ships_from": null,
      "delivery_text": null,
      "first_seen": 1777713960395,
      "last_seen": 1777713960395,
      "is_buybox": false
    },
    {
      "offer_id": "B0BHD9TS9Q__keepa_new_1",
      "asin": "B0BHD9TS9Q",
      "model": "4090",
      "title": "ASUS TUF Gaming NVIDIA GeForce RTX 4090 OC Edition Gaming Graphics Card (24GB GDDR6X, PCIe 4.0, HDMI 2.1a, DisplayPort 1.4a, Dual Ball Bearing Axial Fans)",
      "condition": "new",
      "condition_note": "lowest current new (Keepa)",
      "price_usd": 3695,
      "currency": "USD",
      "seller": null,
      "seller_id": null,
      "seller_rating": null,
      "seller_rating_count": null,
      "ships_from": null,
      "delivery_text": null,
      "first_seen": 1777713960395,
      "last_seen": 1777713960395,
      "is_buybox": true
    },
    {
      "offer_id": "B0BHD9TS9Q__keepa_used-good_2",
      "asin": "B0BHD9TS9Q",
      "model": "4090",
      "title": "ASUS TUF Gaming NVIDIA GeForce RTX 4090 OC Edition Gaming Graphics Card (24GB GDDR6X, PCIe 4.0, HDMI 2.1a, DisplayPort 1.4a, Dual Ball Bearing Axial Fans)",
      "condition": "used-good",
      "condition_note": "lowest current used (Keepa)",
      "price_usd": 3532.42,
      "currency": "USD",
      "seller": null,
      "seller_id": null,
      "seller_rating": null,
      "seller_rating_count": null,
      "ships_from": null,
      "delivery_text": null,
      "first_seen": 1777713960395,
      "last_seen": 1777713960395,
      "is_buybox": false
    },
    {
      "offer_id": "B09YD4FJ5R__keepa_new_1",
      "asin": "B09YD4FJ5R",
      "model": "4090",
      "title": "MSI GeForce RTX 4090 SUPRIM Liquid X 24G Gaming Graphics Card - 24GB GDDR6X, 2625 MHz, PCI Express Gen 4, 384-bit, 3X DP v 1.4a, HDMI 2.1a (Supports 4K & 8K HDR)",
      "condition": "new",
      "condition_note": "lowest current new (Keepa)",
      "price_usd": 3495,
      "currency": "USD",
      "seller": null,
      "seller_id": null,
      "seller_rating": null,
      "seller_rating_count": null,
      "ships_from": null,
      "delivery_text": null,
      "first_seen": 1777713960395,
      "last_seen": 1777713960395,
      "is_buybox": true
    },
    {
      "offer_id": "B09YD4FJ5R__keepa_used-good_2",
      "asin": "B09YD4FJ5R",
      "model": "4090",
      "title": "MSI GeForce RTX 4090 SUPRIM Liquid X 24G Gaming Graphics Card - 24GB GDDR6X, 2625 MHz, PCI Express Gen 4, 384-bit, 3X DP v 1.4a, HDMI 2.1a (Supports 4K & 8K HDR)",
      "condition": "used-good",
      "condition_note": "lowest current used (Keepa)",
      "price_usd": 2899.99,
      "currency": "USD",
      "seller": null,
      "seller_id": null,
      "seller_rating": null,
      "seller_rating_count": null,
      "ships_from": null,
      "delivery_text": null,
      "first_seen": 1777713960395,
      "last_seen": 1777713960395,
      "is_buybox": false
    },
    {
      "offer_id": "B09GWB753L__keepa_new_1",
      "asin": "B09GWB753L",
      "model": "3090",
      "title": "NVIDIA GeForce RTX 3090 Founders Edition Graphics Card (Renewed)",
      "condition": "new",
      "condition_note": "lowest current new (Keepa)",
      "price_usd": 1439.97,
      "currency": "USD",
      "seller": null,
      "seller_id": null,
      "seller_rating": null,
      "seller_rating_count": null,
      "ships_from": null,
      "delivery_text": null,
      "first_seen": 1777713960395,
      "last_seen": 1777713960395,
      "is_buybox": true
    },
    {
      "offer_id": "B095M8QCNL__keepa_new_1",
      "asin": "B095M8QCNL",
      "model": "3090",
      "title": "MSI Gaming GeForce RTX 3090 24GB GDRR6X 384-Bit HDMI/DP Nvlink Tri-Frozr 2 Ampere Architecture OC Graphics Card (RTX 3090 GAMING X TRIO 24G) (Renewed)",
      "condition": "new",
      "condition_note": "lowest current new (Keepa)",
      "price_usd": 1449.97,
      "currency": "USD",
      "seller": null,
      "seller_id": null,
      "seller_rating": null,
      "seller_rating_count": null,
      "ships_from": null,
      "delivery_text": null,
      "first_seen": 1777713960395,
      "last_seen": 1777713960395,
      "is_buybox": true
    },
    {
      "offer_id": "B09X4JVZB5__keepa_new_1",
      "asin": "B09X4JVZB5",
      "model": "3090",
      "title": "Nvidia GeForce RTX 3090 Ti Founders Edition",
      "condition": "new",
      "condition_note": "lowest current new (Keepa)",
      "price_usd": 2079.99,
      "currency": "USD",
      "seller": null,
      "seller_id": null,
      "seller_rating": null,
      "seller_rating_count": null,
      "ships_from": null,
      "delivery_text": null,
      "first_seen": 1777713960395,
      "last_seen": 1777713960395,
      "is_buybox": true
    },
    {
      "offer_id": "B09Y2K9G3X__keepa_new_1",
      "asin": "B09Y2K9G3X",
      "model": "3090",
      "title": "Gigabyte 24GB NVIDIA GeForce RTX 3090 Turbo GDDR6X Graphics Card Model GV-N3090TURBO-24GD (Renewed)",
      "condition": "new",
      "condition_note": "lowest current new (Keepa)",
      "price_usd": 1349.99,
      "currency": "USD",
      "seller": null,
      "seller_id": null,
      "seller_rating": null,
      "seller_rating_count": null,
      "ships_from": null,
      "delivery_text": null,
      "first_seen": 1777713960395,
      "last_seen": 1777713960395,
      "is_buybox": true
    },
    {
      "offer_id": "B08KHKDTSJ__keepa_new_1",
      "asin": "B08KHKDTSJ",
      "model": "3090",
      "title": "Gigabyte 24GB NVIDIA GeForce RTX 3090 Turbo GDDR6X Graphics Card Model GV-N3090TURBO-24GD",
      "condition": "new",
      "condition_note": "lowest current new (Keepa)",
      "price_usd": 1999.9,
      "currency": "USD",
      "seller": null,
      "seller_id": null,
      "seller_rating": null,
      "seller_rating_count": null,
      "ships_from": null,
      "delivery_text": null,
      "first_seen": 1777713960395,
      "last_seen": 1777713960395,
      "is_buybox": true
    },
    {
      "offer_id": "B08KHKDTSJ__keepa_used-good_2",
      "asin": "B08KHKDTSJ",
      "model": "3090",
      "title": "Gigabyte 24GB NVIDIA GeForce RTX 3090 Turbo GDDR6X Graphics Card Model GV-N3090TURBO-24GD",
      "condition": "used-good",
      "condition_note": "lowest current used (Keepa)",
      "price_usd": 1559.99,
      "currency": "USD",
      "seller": null,
      "seller_id": null,
      "seller_rating": null,
      "seller_rating_count": null,
      "ships_from": null,
      "delivery_text": null,
      "first_seen": 1777713960395,
      "last_seen": 1777713960395,
      "is_buybox": false
    },
    {
      "offer_id": "B08HR6ZBYJ__keepa_new_1",
      "asin": "B08HR6ZBYJ",
      "model": "3090",
      "title": "nVidia GeForce RTX 3090 Founders Edition Graphics Card",
      "condition": "new",
      "condition_note": "lowest current new (Keepa)",
      "price_usd": 1927.16,
      "currency": "USD",
      "seller": null,
      "seller_id": null,
      "seller_rating": null,
      "seller_rating_count": null,
      "ships_from": null,
      "delivery_text": null,
      "first_seen": 1777713960395,
      "last_seen": 1777713960395,
      "is_buybox": true
    },
    {
      "offer_id": "B08HR6ZBYJ__keepa_used-good_2",
      "asin": "B08HR6ZBYJ",
      "model": "3090",
      "title": "nVidia GeForce RTX 3090 Founders Edition Graphics Card",
      "condition": "used-good",
      "condition_note": "lowest current used (Keepa)",
      "price_usd": 1389.99,
      "currency": "USD",
      "seller": null,
      "seller_id": null,
      "seller_rating": null,
      "seller_rating_count": null,
      "ships_from": null,
      "delivery_text": null,
      "first_seen": 1777713960395,
      "last_seen": 1777713960395,
      "is_buybox": false
    },
    {
      "offer_id": "B0FK5XN5DN__keepa_new_1",
      "asin": "B0FK5XN5DN",
      "model": "3090",
      "title": "HP OMEN Gaming Desktop PC, Intel Core i9-10850K Processor (10 Cores, Up to 5.2GHz), NVIDIA GeForce RTX 3090 24GB, 32GB DDR4 RAM, 1TB PCIe SSD, Wi-Fi 6, BT, VR Ready, USB-C, HDMI/DP, Windows 10",
      "condition": "new",
      "condition_note": "lowest current new (Keepa)",
      "price_usd": 2399.99,
      "currency": "USD",
      "seller": null,
      "seller_id": null,
      "seller_rating": null,
      "seller_rating_count": null,
      "ships_from": null,
      "delivery_text": null,
      "first_seen": 1777713960395,
      "last_seen": 1777713960395,
      "is_buybox": true
    },
    {
      "offer_id": "B0CDDGMP1N__keepa_new_1",
      "asin": "B0CDDGMP1N",
      "model": "3090",
      "title": "Dell M8HMD NVIDIA GeForce RTX 3090 24GB Graphics Card - GDDR6X - Pcie 4.0 X16 (Renewed)",
      "condition": "new",
      "condition_note": "lowest current new (Keepa)",
      "price_usd": 1384.99,
      "currency": "USD",
      "seller": null,
      "seller_id": null,
      "seller_rating": null,
      "seller_rating_count": null,
      "ships_from": null,
      "delivery_text": null,
      "first_seen": 1777713960395,
      "last_seen": 1777713960395,
      "is_buybox": true
    },
    {
      "offer_id": "B0BKH8HDWK__keepa_new_1",
      "asin": "B0BKH8HDWK",
      "model": "3090",
      "title": "Nvidia RTX 3090 TI Founders Edition (Renewed) Founder Video Graphics Card",
      "condition": "new",
      "condition_note": "lowest current new (Keepa)",
      "price_usd": 1999.99,
      "currency": "USD",
      "seller": null,
      "seller_id": null,
      "seller_rating": null,
      "seller_rating_count": null,
      "ships_from": null,
      "delivery_text": null,
      "first_seen": 1777713960395,
      "last_seen": 1777713960395,
      "is_buybox": true
    },
    {
      "offer_id": "B08KTWVHQP__keepa_new_1",
      "asin": "B08KTWVHQP",
      "model": "3090",
      "title": "GIGABYTE AORUS GeForce RTX 3090 Xtreme 24G Graphics Card, Max Covered Cooling, 24GB 384-bit GDDR6X, GV-N3090AORUS X-24GD Video Card",
      "condition": "new",
      "condition_note": "lowest current new (Keepa)",
      "price_usd": 1798,
      "currency": "USD",
      "seller": null,
      "seller_id": null,
      "seller_rating": null,
      "seller_rating_count": null,
      "ships_from": null,
      "delivery_text": null,
      "first_seen": 1777713960395,
      "last_seen": 1777713960395,
      "is_buybox": true
    },
    {
      "offer_id": "B08KTWVHQP__keepa_used-good_2",
      "asin": "B08KTWVHQP",
      "model": "3090",
      "title": "GIGABYTE AORUS GeForce RTX 3090 Xtreme 24G Graphics Card, Max Covered Cooling, 24GB 384-bit GDDR6X, GV-N3090AORUS X-24GD Video Card",
      "condition": "used-good",
      "condition_note": "lowest current used (Keepa)",
      "price_usd": 1522.22,
      "currency": "USD",
      "seller": null,
      "seller_id": null,
      "seller_rating": null,
      "seller_rating_count": null,
      "ships_from": null,
      "delivery_text": null,
      "first_seen": 1777713960395,
      "last_seen": 1777713960395,
      "is_buybox": false
    },
    {
      "offer_id": "B09BBS9444__keepa_new_1",
      "asin": "B09BBS9444",
      "model": "3090",
      "title": "ZOTAC Gaming GeForce RTX 3090 Trinity OC 24GB GDDR6X 384-bit 19.5 Gbps PCIE 4.0 Gaming Graphics Card, IceStorm 2.0 Advanced Cooling, Spectra 2.0 RGB Lighting, ZT-A30900J-10P (Renewed)",
      "condition": "new",
      "condition_note": "lowest current new (Keepa)",
      "price_usd": 1329.99,
      "currency": "USD",
      "seller": null,
      "seller_id": null,
      "seller_rating": null,
      "seller_rating_count": null,
      "ships_from": null,
      "delivery_text": null,
      "first_seen": 1777713960395,
      "last_seen": 1777713960395,
      "is_buybox": true
    },
    {
      "offer_id": "B09BBS9444__keepa_refurbished_2",
      "asin": "B09BBS9444",
      "model": "3090",
      "title": "ZOTAC Gaming GeForce RTX 3090 Trinity OC 24GB GDDR6X 384-bit 19.5 Gbps PCIE 4.0 Gaming Graphics Card, IceStorm 2.0 Advanced Cooling, Spectra 2.0 RGB Lighting, ZT-A30900J-10P (Renewed)",
      "condition": "refurbished",
      "condition_note": "lowest current refurbished (Keepa)",
      "price_usd": 1329.99,
      "currency": "USD",
      "seller": null,
      "seller_id": null,
      "seller_rating": null,
      "seller_rating_count": null,
      "ships_from": null,
      "delivery_text": null,
      "first_seen": 1777713960395,
      "last_seen": 1777713960395,
      "is_buybox": false
    },
    {
      "offer_id": "B0BDXTS8FC__keepa_new_1",
      "asin": "B0BDXTS8FC",
      "model": "3090",
      "title": "MSI Gaming GeForce RTX 3090 Ti 24GB GDRR6X 384-Bit HDMI/DP Nvlink Tri-Frozr Ampere Architecture OC Graphics Card (RTX 3090 Ti Gaming X Trio 24G) (Renewed)",
      "condition": "new",
      "condition_note": "lowest current new (Keepa)",
      "price_usd": 1549.99,
      "currency": "USD",
      "seller": null,
      "seller_id": null,
      "seller_rating": null,
      "seller_rating_count": null,
      "ships_from": null,
      "delivery_text": null,
      "first_seen": 1777713960395,
      "last_seen": 1777713960395,
      "is_buybox": true
    },
    {
      "offer_id": "B0F6VYF3RY__keepa_new_1",
      "asin": "B0F6VYF3RY",
      "model": "5090",
      "title": "msi Ventus 3X GeForce RTX 5090 OC Edition 32GB GDDR7, PCI Express Gen 5, Clocks Extreme: 2452 MHz, CUDA CORES 21760 Units, Memory Speed 28 Gbps. Bundle with Targus dockstation and Alinware Backpack",
      "condition": "new",
      "condition_note": "lowest current new (Keepa)",
      "price_usd": 4019.97,
      "currency": "USD",
      "seller": null,
      "seller_id": null,
      "seller_rating": null,
      "seller_rating_count": null,
      "ships_from": null,
      "delivery_text": null,
      "first_seen": 1777713960395,
      "last_seen": 1777713960395,
      "is_buybox": true
    },
    {
      "offer_id": "B0DT7L98J1__keepa_new_1",
      "asin": "B0DT7L98J1",
      "model": "5090",
      "title": "msi Gaming RTX 5090 32G Gaming Trio OC Graphics Card (32GB GDDR7, 512-bit, Extreme Performance: 2497 MHz, DisplayPort x3 2.1a, HDMI 2.1b, NVIDIA Blackwell Architecture)",
      "condition": "new",
      "condition_note": "lowest current new (Keepa)",
      "price_usd": 3789.99,
      "currency": "USD",
      "seller": null,
      "seller_id": null,
      "seller_rating": null,
      "seller_rating_count": null,
      "ships_from": null,
      "delivery_text": null,
      "first_seen": 1777713960395,
      "last_seen": 1777713960395,
      "is_buybox": true
    },
    {
      "offer_id": "B0DT7L98J1__keepa_used-good_2",
      "asin": "B0DT7L98J1",
      "model": "5090",
      "title": "msi Gaming RTX 5090 32G Gaming Trio OC Graphics Card (32GB GDDR7, 512-bit, Extreme Performance: 2497 MHz, DisplayPort x3 2.1a, HDMI 2.1b, NVIDIA Blackwell Architecture)",
      "condition": "used-good",
      "condition_note": "lowest current used (Keepa)",
      "price_usd": 3759.99,
      "currency": "USD",
      "seller": null,
      "seller_id": null,
      "seller_rating": null,
      "seller_rating_count": null,
      "ships_from": null,
      "delivery_text": null,
      "first_seen": 1777713960395,
      "last_seen": 1777713960395,
      "is_buybox": false
    },
    {
      "offer_id": "B0GJBFKRBP__keepa_new_1",
      "asin": "B0GJBFKRBP",
      "model": "5090",
      "title": "Panorama XL RTX 5090, AMD Ryzen 9 9900X, 96GB DDR5 RAM, 4TB NVMe Gen4 SSD, HDMI, RJ45, Windows 11 Pro, 3 Year Warranty, RGB Keyboard+Mouse, WiFi 7+BT, HDMI, Prebuilt WaterCooled Gaming Desktop PC",
      "condition": "new",
      "condition_note": "lowest current new (Keepa)",
      "price_usd": 6899.99,
      "currency": "USD",
      "seller": null,
      "seller_id": null,
      "seller_rating": null,
      "seller_rating_count": null,
      "ships_from": null,
      "delivery_text": null,
      "first_seen": 1777713960395,
      "last_seen": 1777713960395,
      "is_buybox": true
    },
    {
      "offer_id": "B0FJVQYGQW__keepa_new_1",
      "asin": "B0FJVQYGQW",
      "model": "5090",
      "title": "ASUS ROG Astral GeForce RTX 5090 BTF OC Edition, 32GB GDDR7, 3.8-Slot, 1000W Support",
      "condition": "new",
      "condition_note": "lowest current new (Keepa)",
      "price_usd": 3899.99,
      "currency": "USD",
      "seller": null,
      "seller_id": null,
      "seller_rating": null,
      "seller_rating_count": null,
      "ships_from": null,
      "delivery_text": null,
      "first_seen": 1777713960395,
      "last_seen": 1777713960395,
      "is_buybox": true
    },
    {
      "offer_id": "B0FJVQYGQW__keepa_used-good_2",
      "asin": "B0FJVQYGQW",
      "model": "5090",
      "title": "ASUS ROG Astral GeForce RTX 5090 BTF OC Edition, 32GB GDDR7, 3.8-Slot, 1000W Support",
      "condition": "used-good",
      "condition_note": "lowest current used (Keepa)",
      "price_usd": 3704.99,
      "currency": "USD",
      "seller": null,
      "seller_id": null,
      "seller_rating": null,
      "seller_rating_count": null,
      "ships_from": null,
      "delivery_text": null,
      "first_seen": 1777713960395,
      "last_seen": 1777713960395,
      "is_buybox": false
    },
    {
      "offer_id": "B0DT7GMXHB__keepa_new_1",
      "asin": "B0DT7GMXHB",
      "model": "5090",
      "title": "GIGABYTE GeForce RTX 5090 WINDFORCE OC 32G Graphics Card, WINDFORCE Cooling System, 32GB 512-bit GDDR7, GV-N5090WF3OC-32GD Video Card",
      "condition": "new",
      "condition_note": "lowest current new (Keepa)",
      "price_usd": 3887.3,
      "currency": "USD",
      "seller": null,
      "seller_id": null,
      "seller_rating": null,
      "seller_rating_count": null,
      "ships_from": null,
      "delivery_text": null,
      "first_seen": 1777713960395,
      "last_seen": 1777713960395,
      "is_buybox": true
    },
    {
      "offer_id": "B0DT7GMXHB__keepa_used-good_2",
      "asin": "B0DT7GMXHB",
      "model": "5090",
      "title": "GIGABYTE GeForce RTX 5090 WINDFORCE OC 32G Graphics Card, WINDFORCE Cooling System, 32GB 512-bit GDDR7, GV-N5090WF3OC-32GD Video Card",
      "condition": "used-good",
      "condition_note": "lowest current used (Keepa)",
      "price_usd": 3679.99,
      "currency": "USD",
      "seller": null,
      "seller_id": null,
      "seller_rating": null,
      "seller_rating_count": null,
      "ships_from": null,
      "delivery_text": null,
      "first_seen": 1777713960395,
      "last_seen": 1777713960395,
      "is_buybox": false
    },
    {
      "offer_id": "B0GRFXRSZV__keepa_new_1",
      "asin": "B0GRFXRSZV",
      "model": "5090",
      "title": "ASUS ROG Matrix Platinum GeForce RTX 5090 OC 30th-Anniversary Edition Gaming Graphics Card, 32GB GDDR7, PCIe 5.0, 512-bit, Liquid Metal Cooling, DisplayPort 2.1b, HDMI 2.1b, MTX5090P32G30TH",
      "condition": "new",
      "condition_note": "lowest current new (Keepa)",
      "price_usd": 4989.99,
      "currency": "USD",
      "seller": null,
      "seller_id": null,
      "seller_rating": null,
      "seller_rating_count": null,
      "ships_from": null,
      "delivery_text": null,
      "first_seen": 1777713960395,
      "last_seen": 1777713960395,
      "is_buybox": true
    },
    {
      "offer_id": "B0F1ZLXNJS__keepa_new_1",
      "asin": "B0F1ZLXNJS",
      "model": "5090",
      "title": "ZOTAC Gaming GeForce RTX 5090 Solid 32GB GDDR7 Reflex 2 RTX AI DLSS4",
      "condition": "new",
      "condition_note": "lowest current new (Keepa)",
      "price_usd": 4429.99,
      "currency": "USD",
      "seller": null,
      "seller_id": null,
      "seller_rating": null,
      "seller_rating_count": null,
      "ships_from": null,
      "delivery_text": null,
      "first_seen": 1777713960395,
      "last_seen": 1777713960395,
      "is_buybox": true
    },
    {
      "offer_id": "B0GH2SDC11__keepa_new_1",
      "asin": "B0GH2SDC11",
      "model": "5090",
      "title": "Mantis V2 - RTX 5090, 24-Core i9-14900KF, 96GB DDR5 RAM, 4TB NVME Gen4 SSD, 360mm Liquid Cooled Gaming Desktop PC w/Windows 11 Pro, 3-Year Warranty, RGB Keyboard+Mouse, Internal Wi-Fi 6E, DP & HDMI",
      "condition": "new",
      "condition_note": "lowest current new (Keepa)",
      "price_usd": 6599.99,
      "currency": "USD",
      "seller": null,
      "seller_id": null,
      "seller_rating": null,
      "seller_rating_count": null,
      "ships_from": null,
      "delivery_text": null,
      "first_seen": 1777713960395,
      "last_seen": 1777713960395,
      "is_buybox": true
    },
    {
      "offer_id": "B0DTHWSR1X__keepa_new_1",
      "asin": "B0DTHWSR1X",
      "model": "5090",
      "title": "ASUS TUF Gaming GeForce RTX 5090 OC Edition 32GB GDDR7 Gaming Graphics Card (Nvidia GeForce RTX5090, 3.6 Slot Design, PCIe 5.0, 2X HDMI 2.1b, 3X DisplayPort 2.1a, TUF-RTX5090-O32G-GAMING)",
      "condition": "new",
      "condition_note": "lowest current new (Keepa)",
      "price_usd": 3999.97,
      "currency": "USD",
      "seller": null,
      "seller_id": null,
      "seller_rating": null,
      "seller_rating_count": null,
      "ships_from": null,
      "delivery_text": null,
      "first_seen": 1777713960395,
      "last_seen": 1777713960395,
      "is_buybox": true
    },
    {
      "offer_id": "B0DT7KGND2__keepa_new_1",
      "asin": "B0DT7KGND2",
      "model": "5090",
      "title": "msi Gaming RTX 5090 32G Vanguard SOC Graphics Card (32GB GDDR7, 512-bit, Extreme Performance: 2527 MHz, DisplayPort x3 2.1a, HDMI 2.1b, NVIDIA Blackwell Architecture)",
      "condition": "new",
      "condition_note": "lowest current new (Keepa)",
      "price_usd": 4080,
      "currency": "USD",
      "seller": null,
      "seller_id": null,
      "seller_rating": null,
      "seller_rating_count": null,
      "ships_from": null,
      "delivery_text": null,
      "first_seen": 1777713960395,
      "last_seen": 1777713960395,
      "is_buybox": true
    },
    {
      "offer_id": "B0GL51ZPSV__keepa_new_1",
      "asin": "B0GL51ZPSV",
      "model": "5090",
      "title": "msi Gaming RTX 5090 32G Lightning Z Graphics Card (32GB GDDR7, 512-bit, Extreme Performance: 2775 MHz, DisplayPort x3 2.1a, HDMI 2.1b, NVIDIA Blackwell Architecture)",
      "condition": "new",
      "condition_note": "lowest current new (Keepa)",
      "price_usd": 6199.99,
      "currency": "USD",
      "seller": null,
      "seller_id": null,
      "seller_rating": null,
      "seller_rating_count": null,
      "ships_from": null,
      "delivery_text": null,
      "first_seen": 1777713960395,
      "last_seen": 1777713960395,
      "is_buybox": true
    },
    {
      "offer_id": "B0DT7JYTXQ__keepa_new_1",
      "asin": "B0DT7JYTXQ",
      "model": "5090",
      "title": "msi Gaming RTX 5090 32G SUPRIM SOC Graphics Card (32GB GDDR7, 512-bit, Extreme Performance: 2580 MHz, DisplayPort x3 2.1a, HDMI 2.1b, NVIDIA Blackwell Architecture)",
      "condition": "new",
      "condition_note": "lowest current new (Keepa)",
      "price_usd": 4589.97,
      "currency": "USD",
      "seller": null,
      "seller_id": null,
      "seller_rating": null,
      "seller_rating_count": null,
      "ships_from": null,
      "delivery_text": null,
      "first_seen": 1777713960395,
      "last_seen": 1777713960395,
      "is_buybox": true
    },
    {
      "offer_id": "B0DT7JYTXQ__keepa_used-good_2",
      "asin": "B0DT7JYTXQ",
      "model": "5090",
      "title": "msi Gaming RTX 5090 32G SUPRIM SOC Graphics Card (32GB GDDR7, 512-bit, Extreme Performance: 2580 MHz, DisplayPort x3 2.1a, HDMI 2.1b, NVIDIA Blackwell Architecture)",
      "condition": "used-good",
      "condition_note": "lowest current used (Keepa)",
      "price_usd": 4933.22,
      "currency": "USD",
      "seller": null,
      "seller_id": null,
      "seller_rating": null,
      "seller_rating_count": null,
      "ships_from": null,
      "delivery_text": null,
      "first_seen": 1777713960395,
      "last_seen": 1777713960395,
      "is_buybox": false
    },
    {
      "offer_id": "B0GGMNQ8J4__keepa_new_1",
      "asin": "B0GGMNQ8J4",
      "model": "5090",
      "title": "Mantis V2 - RTX 5090, Ryzen 9 9950X3D, 128GB DDR5 RAM, 4TB NVMe Gen4 SSD, 6TB HDD, Windows 11 Pro, 3 Year Warranty, HDMI+DP, WaterCooled, RGB Keyboard+Mouse, WiFi 6E+BT, Prebuilt Gaming Desktop PC",
      "condition": "new",
      "condition_note": "lowest current new (Keepa)",
      "price_usd": 7499.99,
      "currency": "USD",
      "seller": null,
      "seller_id": null,
      "seller_rating": null,
      "seller_rating_count": null,
      "ships_from": null,
      "delivery_text": null,
      "first_seen": 1777713960395,
      "last_seen": 1777713960395,
      "is_buybox": true
    },
    {
      "offer_id": "B0GJXBMY73__keepa_new_1",
      "asin": "B0GJXBMY73",
      "model": "5090",
      "title": "GIGABYTE GeForce RTX 5090 WINDFORCE 32G Graphics Card, 32GB 512-bit GDDR7, PCIe 5.0, WINDFORCE Cooling System, GV-N5090WF3-32GD Video Card, Bundle with Targus Dock Station and Backpack Alienware",
      "condition": "new",
      "condition_note": "lowest current new (Keepa)",
      "price_usd": 4199.97,
      "currency": "USD",
      "seller": null,
      "seller_id": null,
      "seller_rating": null,
      "seller_rating_count": null,
      "ships_from": null,
      "delivery_text": null,
      "first_seen": 1777317667682,
      "last_seen": 1777317667682,
      "is_buybox": true
    },
    {
      "offer_id": "B0DV64SCM8__keepa_new_1",
      "asin": "B0DV64SCM8",
      "model": "5090",
      "title": "ZOTAC Gaming GeForce RTX 5090 AMP Extreme Infinity DLSS 4 32GB GDDR7 512-bit 28 Gbps PCIE 5.0 Gaming Graphics Card, IceStorm 3.0 Advanced Cooling, Spectra 2.0 ARGB Lighting, ZT-B50900B-10P",
      "condition": "new",
      "condition_note": "lowest current new (Keepa)",
      "price_usd": 3897.95,
      "currency": "USD",
      "seller": null,
      "seller_id": null,
      "seller_rating": null,
      "seller_rating_count": null,
      "ships_from": null,
      "delivery_text": null,
      "first_seen": 1777317667682,
      "last_seen": 1777317667682,
      "is_buybox": true
    },
    {
      "offer_id": "B0FK453MMS__keepa_new_1",
      "asin": "B0FK453MMS",
      "model": "5090",
      "title": "Lenovo Legion Pro 7i Gen 10 16\" Gaming Laptop (2025 Model) Intel Core Ultra 9 275HX 24C, NVIDIA GeForce RTX 5090 24GB, 64GB RAM, 2TB (1TB+1TB) NVMe SSD, 16\" WQXGA OLED 500 nits 240Hz, Windows 11 Home",
      "condition": "new",
      "condition_note": "lowest current new (Keepa)",
      "price_usd": 3999.99,
      "currency": "USD",
      "seller": null,
      "seller_id": null,
      "seller_rating": null,
      "seller_rating_count": null,
      "ships_from": null,
      "delivery_text": null,
      "first_seen": 1777317667682,
      "last_seen": 1777317667682,
      "is_buybox": true
    },
    {
      "offer_id": "B0FK453MMS__keepa_used-good_2",
      "asin": "B0FK453MMS",
      "model": "5090",
      "title": "Lenovo Legion Pro 7i Gen 10 16\" Gaming Laptop (2025 Model) Intel Core Ultra 9 275HX 24C, NVIDIA GeForce RTX 5090 24GB, 64GB RAM, 2TB (1TB+1TB) NVMe SSD, 16\" WQXGA OLED 500 nits 240Hz, Windows 11 Home",
      "condition": "used-good",
      "condition_note": "lowest current used (Keepa)",
      "price_usd": 3509.99,
      "currency": "USD",
      "seller": null,
      "seller_id": null,
      "seller_rating": null,
      "seller_rating_count": null,
      "ships_from": null,
      "delivery_text": null,
      "first_seen": 1777317667682,
      "last_seen": 1777317667682,
      "is_buybox": false
    },
    {
      "offer_id": "B0F4NQZHTW__keepa_new_1",
      "asin": "B0F4NQZHTW",
      "model": "5090",
      "title": "ASUS GeForce RTX 5090 Astral LC Overclocked Liquid Cooled 32GB GDDR7 PCIe 5.0 Graphics Card, 7680 x 4320 Maximum Resolution, Full Height, Triple Slot",
      "condition": "new",
      "condition_note": "lowest current new (Keepa)",
      "price_usd": 4795,
      "currency": "USD",
      "seller": null,
      "seller_id": null,
      "seller_rating": null,
      "seller_rating_count": null,
      "ships_from": null,
      "delivery_text": null,
      "first_seen": 1777317667682,
      "last_seen": 1777317667682,
      "is_buybox": true
    },
    {
      "offer_id": "B0F4NQZHTW__keepa_used-good_2",
      "asin": "B0F4NQZHTW",
      "model": "5090",
      "title": "ASUS GeForce RTX 5090 Astral LC Overclocked Liquid Cooled 32GB GDDR7 PCIe 5.0 Graphics Card, 7680 x 4320 Maximum Resolution, Full Height, Triple Slot",
      "condition": "used-good",
      "condition_note": "lowest current used (Keepa)",
      "price_usd": 3999,
      "currency": "USD",
      "seller": null,
      "seller_id": null,
      "seller_rating": null,
      "seller_rating_count": null,
      "ships_from": null,
      "delivery_text": null,
      "first_seen": 1777317667682,
      "last_seen": 1777317667682,
      "is_buybox": false
    }
  ],
  "products": [
    {
      "asin": "B09YCLG5PB",
      "model": "4090",
      "title": "MSI GeForce RTX 4090 Gaming X Trio 24G Gaming Graphics Card - 24GB GDDR6X, 2595 MHz, PCI Express Gen 4, 384-bit, 3X DP v 1.4a, HDMI 2.1a (Supports 4K & 8K HDR)",
      "thumbnail_url": null,
      "last_refreshed": 1777713960395
    },
    {
      "asin": "B0BJFRT43X",
      "model": "4090",
      "title": "VIPERA NVIDIA GeForce RTX 4090 Founders Edition Graphic Card",
      "thumbnail_url": null,
      "last_refreshed": 1777713960395
    },
    {
      "asin": "B0BHD9TS9Q",
      "model": "4090",
      "title": "ASUS TUF Gaming NVIDIA GeForce RTX 4090 OC Edition Gaming Graphics Card (24GB GDDR6X, PCIe 4.0, HDMI 2.1a, DisplayPort 1.4a, Dual Ball Bearing Axial Fans)",
      "thumbnail_url": null,
      "last_refreshed": 1777713960395
    },
    {
      "asin": "B0CPB3P36K",
      "model": "4090",
      "title": "GeForce VIPERA NVIDIA GeForce RTX 4090 Founders Edition Graphic Card (Renewed)",
      "thumbnail_url": null,
      "last_refreshed": 1777713960395
    },
    {
      "asin": "B09YD4FJ5R",
      "model": "4090",
      "title": "MSI GeForce RTX 4090 SUPRIM Liquid X 24G Gaming Graphics Card - 24GB GDDR6X, 2625 MHz, PCI Express Gen 4, 384-bit, 3X DP v 1.4a, HDMI 2.1a (Supports 4K & 8K HDR)",
      "thumbnail_url": null,
      "last_refreshed": 1777713960395
    },
    {
      "asin": "B09GWB753L",
      "model": "3090",
      "title": "NVIDIA GeForce RTX 3090 Founders Edition Graphics Card (Renewed)",
      "thumbnail_url": null,
      "last_refreshed": 1777713960395
    },
    {
      "asin": "B095M8QCNL",
      "model": "3090",
      "title": "MSI Gaming GeForce RTX 3090 24GB GDRR6X 384-Bit HDMI/DP Nvlink Tri-Frozr 2 Ampere Architecture OC Graphics Card (RTX 3090 GAMING X TRIO 24G) (Renewed)",
      "thumbnail_url": null,
      "last_refreshed": 1777713960395
    },
    {
      "asin": "B09X4JVZB5",
      "model": "3090",
      "title": "Nvidia GeForce RTX 3090 Ti Founders Edition",
      "thumbnail_url": null,
      "last_refreshed": 1777713960395
    },
    {
      "asin": "B09Y2K9G3X",
      "model": "3090",
      "title": "Gigabyte 24GB NVIDIA GeForce RTX 3090 Turbo GDDR6X Graphics Card Model GV-N3090TURBO-24GD (Renewed)",
      "thumbnail_url": null,
      "last_refreshed": 1777713960395
    },
    {
      "asin": "B08KHKDTSJ",
      "model": "3090",
      "title": "Gigabyte 24GB NVIDIA GeForce RTX 3090 Turbo GDDR6X Graphics Card Model GV-N3090TURBO-24GD",
      "thumbnail_url": null,
      "last_refreshed": 1777713960395
    },
    {
      "asin": "B08HR6ZBYJ",
      "model": "3090",
      "title": "nVidia GeForce RTX 3090 Founders Edition Graphics Card",
      "thumbnail_url": null,
      "last_refreshed": 1777713960395
    },
    {
      "asin": "B0FK5XN5DN",
      "model": "3090",
      "title": "HP OMEN Gaming Desktop PC, Intel Core i9-10850K Processor (10 Cores, Up to 5.2GHz), NVIDIA GeForce RTX 3090 24GB, 32GB DDR4 RAM, 1TB PCIe SSD, Wi-Fi 6, BT, VR Ready, USB-C, HDMI/DP, Windows 10",
      "thumbnail_url": null,
      "last_refreshed": 1777713960395
    },
    {
      "asin": "B0CDDGMP1N",
      "model": "3090",
      "title": "Dell M8HMD NVIDIA GeForce RTX 3090 24GB Graphics Card - GDDR6X - Pcie 4.0 X16 (Renewed)",
      "thumbnail_url": null,
      "last_refreshed": 1777713960395
    },
    {
      "asin": "B0BKH8HDWK",
      "model": "3090",
      "title": "Nvidia RTX 3090 TI Founders Edition (Renewed) Founder Video Graphics Card",
      "thumbnail_url": null,
      "last_refreshed": 1777713960395
    },
    {
      "asin": "B08KTWVHQP",
      "model": "3090",
      "title": "GIGABYTE AORUS GeForce RTX 3090 Xtreme 24G Graphics Card, Max Covered Cooling, 24GB 384-bit GDDR6X, GV-N3090AORUS X-24GD Video Card",
      "thumbnail_url": null,
      "last_refreshed": 1777713960395
    },
    {
      "asin": "B09BBS9444",
      "model": "3090",
      "title": "ZOTAC Gaming GeForce RTX 3090 Trinity OC 24GB GDDR6X 384-bit 19.5 Gbps PCIE 4.0 Gaming Graphics Card, IceStorm 2.0 Advanced Cooling, Spectra 2.0 RGB Lighting, ZT-A30900J-10P (Renewed)",
      "thumbnail_url": null,
      "last_refreshed": 1777713960395
    },
    {
      "asin": "B0BDXTS8FC",
      "model": "3090",
      "title": "MSI Gaming GeForce RTX 3090 Ti 24GB GDRR6X 384-Bit HDMI/DP Nvlink Tri-Frozr Ampere Architecture OC Graphics Card (RTX 3090 Ti Gaming X Trio 24G) (Renewed)",
      "thumbnail_url": null,
      "last_refreshed": 1777713960395
    },
    {
      "asin": "B0F6VYF3RY",
      "model": "5090",
      "title": "msi Ventus 3X GeForce RTX 5090 OC Edition 32GB GDDR7, PCI Express Gen 5, Clocks Extreme: 2452 MHz, CUDA CORES 21760 Units, Memory Speed 28 Gbps. Bundle with Targus dockstation and Alinware Backpack",
      "thumbnail_url": null,
      "last_refreshed": 1777713960395
    },
    {
      "asin": "B0DT7L98J1",
      "model": "5090",
      "title": "msi Gaming RTX 5090 32G Gaming Trio OC Graphics Card (32GB GDDR7, 512-bit, Extreme Performance: 2497 MHz, DisplayPort x3 2.1a, HDMI 2.1b, NVIDIA Blackwell Architecture)",
      "thumbnail_url": null,
      "last_refreshed": 1777713960395
    },
    {
      "asin": "B0GJBFKRBP",
      "model": "5090",
      "title": "Panorama XL RTX 5090, AMD Ryzen 9 9900X, 96GB DDR5 RAM, 4TB NVMe Gen4 SSD, HDMI, RJ45, Windows 11 Pro, 3 Year Warranty, RGB Keyboard+Mouse, WiFi 7+BT, HDMI, Prebuilt WaterCooled Gaming Desktop PC",
      "thumbnail_url": null,
      "last_refreshed": 1777713960395
    },
    {
      "asin": "B0FJVQYGQW",
      "model": "5090",
      "title": "ASUS ROG Astral GeForce RTX 5090 BTF OC Edition, 32GB GDDR7, 3.8-Slot, 1000W Support",
      "thumbnail_url": null,
      "last_refreshed": 1777713960395
    },
    {
      "asin": "B0DT7GMXHB",
      "model": "5090",
      "title": "GIGABYTE GeForce RTX 5090 WINDFORCE OC 32G Graphics Card, WINDFORCE Cooling System, 32GB 512-bit GDDR7, GV-N5090WF3OC-32GD Video Card",
      "thumbnail_url": null,
      "last_refreshed": 1777713960395
    },
    {
      "asin": "B0GRFXRSZV",
      "model": "5090",
      "title": "ASUS ROG Matrix Platinum GeForce RTX 5090 OC 30th-Anniversary Edition Gaming Graphics Card, 32GB GDDR7, PCIe 5.0, 512-bit, Liquid Metal Cooling, DisplayPort 2.1b, HDMI 2.1b, MTX5090P32G30TH",
      "thumbnail_url": null,
      "last_refreshed": 1777713960395
    },
    {
      "asin": "B0F1ZLXNJS",
      "model": "5090",
      "title": "ZOTAC Gaming GeForce RTX 5090 Solid 32GB GDDR7 Reflex 2 RTX AI DLSS4",
      "thumbnail_url": null,
      "last_refreshed": 1777713960395
    },
    {
      "asin": "B0GH2SDC11",
      "model": "5090",
      "title": "Mantis V2 - RTX 5090, 24-Core i9-14900KF, 96GB DDR5 RAM, 4TB NVME Gen4 SSD, 360mm Liquid Cooled Gaming Desktop PC w/Windows 11 Pro, 3-Year Warranty, RGB Keyboard+Mouse, Internal Wi-Fi 6E, DP & HDMI",
      "thumbnail_url": null,
      "last_refreshed": 1777713960395
    },
    {
      "asin": "B0DTHWSR1X",
      "model": "5090",
      "title": "ASUS TUF Gaming GeForce RTX 5090 OC Edition 32GB GDDR7 Gaming Graphics Card (Nvidia GeForce RTX5090, 3.6 Slot Design, PCIe 5.0, 2X HDMI 2.1b, 3X DisplayPort 2.1a, TUF-RTX5090-O32G-GAMING)",
      "thumbnail_url": null,
      "last_refreshed": 1777713960395
    },
    {
      "asin": "B0DT7KGND2",
      "model": "5090",
      "title": "msi Gaming RTX 5090 32G Vanguard SOC Graphics Card (32GB GDDR7, 512-bit, Extreme Performance: 2527 MHz, DisplayPort x3 2.1a, HDMI 2.1b, NVIDIA Blackwell Architecture)",
      "thumbnail_url": null,
      "last_refreshed": 1777713960395
    },
    {
      "asin": "B0GL51ZPSV",
      "model": "5090",
      "title": "msi Gaming RTX 5090 32G Lightning Z Graphics Card (32GB GDDR7, 512-bit, Extreme Performance: 2775 MHz, DisplayPort x3 2.1a, HDMI 2.1b, NVIDIA Blackwell Architecture)",
      "thumbnail_url": null,
      "last_refreshed": 1777713960395
    },
    {
      "asin": "B0DT7JYTXQ",
      "model": "5090",
      "title": "msi Gaming RTX 5090 32G SUPRIM SOC Graphics Card (32GB GDDR7, 512-bit, Extreme Performance: 2580 MHz, DisplayPort x3 2.1a, HDMI 2.1b, NVIDIA Blackwell Architecture)",
      "thumbnail_url": null,
      "last_refreshed": 1777713960395
    },
    {
      "asin": "B0GGMNQ8J4",
      "model": "5090",
      "title": "Mantis V2 - RTX 5090, Ryzen 9 9950X3D, 128GB DDR5 RAM, 4TB NVMe Gen4 SSD, 6TB HDD, Windows 11 Pro, 3 Year Warranty, HDMI+DP, WaterCooled, RGB Keyboard+Mouse, WiFi 6E+BT, Prebuilt Gaming Desktop PC",
      "thumbnail_url": null,
      "last_refreshed": 1777713960395
    },
    {
      "asin": "B0GJXBMY73",
      "model": "5090",
      "title": "GIGABYTE GeForce RTX 5090 WINDFORCE 32G Graphics Card, 32GB 512-bit GDDR7, PCIe 5.0, WINDFORCE Cooling System, GV-N5090WF3-32GD Video Card, Bundle with Targus Dock Station and Backpack Alienware",
      "thumbnail_url": null,
      "last_refreshed": 1777317667682
    },
    {
      "asin": "B0DV64SCM8",
      "model": "5090",
      "title": "ZOTAC Gaming GeForce RTX 5090 AMP Extreme Infinity DLSS 4 32GB GDDR7 512-bit 28 Gbps PCIE 5.0 Gaming Graphics Card, IceStorm 3.0 Advanced Cooling, Spectra 2.0 ARGB Lighting, ZT-B50900B-10P",
      "thumbnail_url": null,
      "last_refreshed": 1777317667682
    },
    {
      "asin": "B0FK453MMS",
      "model": "5090",
      "title": "Lenovo Legion Pro 7i Gen 10 16\" Gaming Laptop (2025 Model) Intel Core Ultra 9 275HX 24C, NVIDIA GeForce RTX 5090 24GB, 64GB RAM, 2TB (1TB+1TB) NVMe SSD, 16\" WQXGA OLED 500 nits 240Hz, Windows 11 Home",
      "thumbnail_url": null,
      "last_refreshed": 1777317667682
    },
    {
      "asin": "B0F4NQZHTW",
      "model": "5090",
      "title": "ASUS GeForce RTX 5090 Astral LC Overclocked Liquid Cooled 32GB GDDR7 PCIe 5.0 Graphics Card, 7680 x 4320 Maximum Resolution, Full Height, Triple Slot",
      "thumbnail_url": null,
      "last_refreshed": 1777317667682
    }
  ]
}